{
  "applications": [
    {
      "id": "NH25001",
      "studentName": "Nguyễn Văn An",
      "studentDob": "2018-09-15",
      "studentGender": "Nam",
      "parentName": "Nguyễn Văn Ba",
      "parentPhone": "0901234567",
      "address": "Thôn 1, xã Đắk Wil, Cư Jút, Đắk Nông",
      "enrollmentType": "Lớp 1",
      "enrollmentRoute": "Đúng tuyến",
      "isPriority": true,
      "status": "Đã nộp",
      "submittedAt": "2024-07-20T08:30:00.000Z",
      "birthCertUrl": null,
      "residenceProofUrl": null
    },
    {
      "id": "NH25002",
      "studentName": "Trần Thị Bình",
      "studentDob": "2018-05-20",
      "studentGender": "Nữ",
      "parentName": "Trần Văn Bốn",
      "parentPhone": "0987654321",
      "address": "Thôn 2, xã Đắk Wil, Cư Jút, Đắk Nông",
      "enrollmentType": "Lớp 1",
      "enrollmentRoute": "Đúng tuyến",
      "isPriority": false,
      "status": "Đang xét duyệt",
      "submittedAt": "2024-07-21T10:00:00.000Z",
      "birthCertUrl": null,
      "residenceProofUrl": null
    },
    {
      "id": "NH25003",
      "studentName": "Lê Thị Cẩm",
      "studentDob": "2018-01-10",
      "studentGender": "Nữ",
      "parentName": "Lê Văn Năm",
      "parentPhone": "0912345678",
      "address": "Thôn 3, xã Ea Pô, Cư Jút, Đắk Nông",
      "enrollmentType": "Lớp 1",
      "enrollmentRoute": "Trái tuyến",
      "isPriority": false,
      "status": "Đã trúng tuyển",
      "submittedAt": "2024-07-22T14:15:00.000Z",
      "birthCertUrl": null,
      "residenceProofUrl": null
    },
    {
      "id": "NH25004",
      "studentName": "Phạm Văn Dũng",
      "studentDob": "2018-11-05",
      "studentGender": "Nam",
      "parentName": "Phạm Thị Sáu",
      "parentPhone": "0918765432",
      "address": "Thôn 1, xã Đắk Wil, Cư Jút, Đắk Nông",
      "enrollmentType": "Lớp 1",
      "enrollmentRoute": "Đúng tuyến",
      "isPriority": false,
      "status": "Bị từ chối",
      "rejectionReason": "Hồ sơ không hợp lệ.",
      "submittedAt": "2024-07-22T16:00:00.000Z",
      "birthCertUrl": null,
      "residenceProofUrl": null
    },
    {
      "id": "NH25005",
      "studentName": "Hoàng Thị Em",
      "studentDob": "2018-02-28",
      "studentGender": "Nữ",
      "parentName": "Hoàng Văn Bảy",
      "parentPhone": "0935123789",
      "address": "Thôn 2, xã Đắk Wil, Cư Jút, Đắk Nông",
      "enrollmentType": "Lớp 1",
      "enrollmentRoute": "Đúng tuyến",
      "isPriority": false,
      "status": "Đã phân lớp",
      "classId": "CLASS_1A",
      "submittedAt": "2024-07-23T09:45:00.000Z",
      "birthCertUrl": null,
      "residenceProofUrl": null
    }
  ],
  "classes": [
    {
      "id": "CLASS_1A",
      "name": "Lớp 1A",
      "maxSize": 35
    },
    {
      "id": "CLASS_1B",
      "name": "Lớp 1B",
      "maxSize": 35
    },
    {
      "id": "CLASS_1C",
      "name": "Lớp 1C",
      "maxSize": 30
    }
  ],
  "announcement": {
    "title": "Thông báo Tuyển sinh năm học 2024 - 2025",
    "details": [
      {
        "label": "Năm học",
        "value": "2024 - 2025"
      },
      {
        "label": "Đối tượng",
        "value": "Trẻ 6 tuổi (sinh năm 2018) thuộc địa bàn xã Đắk Wil và các khu vực lân cận."
      },
      {
        "label": "Thời gian",
        "value": "Từ ngày 01/08/2024 đến hết ngày 15/08/2024."
      },
      {
        "label": "Hình thức",
        "value": "Đăng ký trực tuyến qua cổng thông tin này."
      }
    ],
    "attachmentUrl": "/uploads/Don_xin_nhap_hoc.pdf",
    "attachmentName": "Don_xin_nhap_hoc.pdf",
    "admittedListUrl": null,
    "admittedListName": null
  },
  "guidelines": [
    {
      "id": "g1",
      "text": "Phụ huynh nhấn nút \"Đăng ký ngay\" và đăng nhập bằng số điện thoại."
    },
    {
      "id": "g2",
      "text": "Điền đầy đủ và chính xác thông tin theo mẫu đăng ký trực tuyến."
    },
    {
      "id": "g3",
      "text": "Tải lên ảnh chụp rõ nét các giấy tờ cần thiết (Giấy khai sinh, Hộ khẩu...)."
    },
    {
      "id": "g4",
      "text": "Kiểm tra lại thông tin và nhấn \"Nộp hồ sơ\" để hoàn tất."
    },
    {
      "id": "g5",
      "text": "Lưu lại Mã hồ sơ để tra cứu kết quả tuyển sinh."
    }
  ],
  "settings": {
    "schoolName": "TRƯỜNG TIỂU HỌC NGUYỄN HUỆ",
    "logoUrl": null,
    "bannerUrl": null
  }
}